{
"Profiles": [
{
    "Name": "Dynamic parent profile",
    "Guid": "dynamic-parent-profile",
    "Blinking Cursor" : true,
    "Cursor Type" : 2,
    "Screen" : -1,
    "Columns" : 80,
    "Rows" : 25,
    "Terminal Type" : "xterm",
    "Window Type" : 1,
    "Scrollback With Status Bar" : false,
    "Scrollback Lines" : 5000,
    "Scrollback in Alternate Screen" : true,
    "Unlimited Scrollback" : false,
    "Non-ASCII Anti Aliased" : true,
    "Sync Title" : false,
    "Disable Window Resizing" : true,
    "Close Sessions On End" : true,
    "Jobs to Ignore" : [
      "rlogin",
      "ssh",
      "slogin",
      "telnet"
    ],
    "Shortcut" : "",
    "BM Growl" : true,
    "Character Encoding" : 4,
    "Tags" : [
      "Parent"
    ],
},
{
    "Name": "Dynamic profile 1",
    "Guid": "dynamic-profile-1",
    "Dynamic Profile Parent Name": "Dynamic parent profile",
    "Tags" : [
    ],
},
{
  "Working Directory" : "\/Users\/david",
  "Prompt Before Closing 2" : 0,
  "Selected Text Color" : {
    "Green Component" : 0,
    "Red Component" : 0,
    "Blue Component" : 0
  },
  "Rows" : 25,
  "Ansi 11 Color" : {
    "Green Component" : 1,
    "Red Component" : 1,
    "Blue Component" : 0.3333333432674408
  },
  "Use Italic Font" : false,
  "Foreground Color" : {
    "Green Component" : 0.73333334922790527,
    "Red Component" : 0.73333334922790527,
    "Blue Component" : 0.73333334922790527
  },
  "Right Option Key Sends" : 0,
  "Character Encoding" : 4,
  "Selection Color" : {
    "Green Component" : 0.8353000283241272,
    "Red Component" : 0.70980000495910645,
    "Blue Component" : 1
  },
  "Triggers" : [

  ],
  "Blend" : 0.30000001192092896,
  "Mouse Reporting" : true,
  "Ansi 4 Color" : {
    "Green Component" : 0,
    "Red Component" : 0,
    "Blue Component" : 0.73333334922790527
  },
  "Non-ASCII Anti Aliased" : true,
  "Sync Title" : false,
  "Disable Window Resizing" : true,
  "Close Sessions On End" : true,
  "Jobs to Ignore" : [
    "rlogin",
    "ssh",
    "slogin",
    "telnet"
  ],
  "Scrollback With Status Bar" : false,
  "Scrollback Lines" : 0,
  "Scrollback in Alternate Screen" : true,
  "Hide After Opening" : false,
  "Flashing Bell" : false,
  "Cursor Guide Color" : {
    "Red Component" : 0.70213186740875244,
    "Color Space" : "sRGB",
    "Blue Component" : 1,
    "Alpha Component" : 0.25,
    "Green Component" : 0.9268307089805603
  },
  "BM Growl" : true,
  "Ansi 3 Color" : {
    "Green Component" : 0.73333334922790527,
    "Red Component" : 0.73333334922790527,
    "Blue Component" : 0
  },
  "Link Color" : {
    "Red Component" : 0,
    "Color Space" : "sRGB",
    "Blue Component" : 0.73423302173614502,
    "Alpha Component" : 1,
    "Green Component" : 0.35916060209274292
  },
  "Shortcut" : "",
  "Background Image Location" : "",
  "Bold Color" : {
    "Green Component" : 1,
    "Red Component" : 1,
    "Blue Component" : 1
  },
  "Unlimited Scrollback" : false,
  "Custom Command" : "No",
  "Smart Selection Rules" : [
    {
      "notes" : "Word bounded by whitespace",
      "regex" : "\\S+",
      "precision" : "low"
    },
    {
      "notes" : "C++ namespace::identifier",
      "regex" : "([a-zA-Z0-9_]+::)+[a-zA-Z0-9_]+",
      "precision" : "normal"
    },
    {
      "notes" : "Paths",
      "regex" : "\\~?\/?([[:letter:][:number:]._-]+\/+)+[[:letter:][:number:]._-]+\/?",
      "precision" : "normal"
    },
    {
      "notes" : "Quoted string",
      "regex" : "@?\"(?:[^\"\\\\]|\\\\.)*\"",
      "precision" : "normal"
    },
    {
      "notes" : "Java\/Python include paths",
      "regex" : "([[:letter:][:number:]._]+\\.)+[[:letter:][:number:]._]+",
      "precision" : "normal"
    },
    {
      "notes" : "mailto URL",
      "regex" : "\\bmailto:([a-z0-9A-Z_]+@)?([a-zA-Z0-9\\-]+\\.)*[a-zA-Z0-9\\-]+\\b",
      "precision" : "normal"
    },
    {
      "notes" : "Obj-C selector",
      "regex" : "@selector\\([^)]+\\)",
      "precision" : "high"
    },
    {
      "notes" : "email address",
      "regex" : "\\b[A-Za-z0-9._%+-]+@[A-Za-z0-9.-]+\\.[A-Za-z]{2,4}\\b",
      "precision" : "high"
    },
    {
      "notes" : "HTTP URL",
      "regex" : "https?:\/\/([a-z0-9A-Z]+(:[a-zA-Z0-9]+)?@)?[a-z0-9A-Z]+(\\.[a-z0-9A-Z]+)*((:[0-9]+)?)(\/[a-zA-Z0-9;\/\\.\\-_+%~?&@=#\\(\\)]*)?",
      "precision" : "very_high"
    },
    {
      "notes" : "SSH URL",
      "regex" : "\\bssh:([a-z0-9A-Z_]+@)?([a-zA-Z0-9\\-]+\\.)*[a-zA-Z0-9\\-]+\\b",
      "precision" : "very_high"
    },
    {
      "notes" : "Telnet URL",
      "regex" : "\\btelnet:([a-z0-9A-Z_]+@)?([a-zA-Z0-9\\-]+\\.)*[a-zA-Z0-9\\-]+\\b",
      "precision" : "very_high"
    }
  ],
  "Keyboard Map" : {
    "0xf700-0x260000" : {
      "Action" : 10,
      "Text" : "[1;6A"
    },
    "0x37-0x40000" : {
      "Action" : 11,
      "Text" : "0x1f"
    },
    "0x32-0x40000" : {
      "Action" : 11,
      "Text" : "0x00"
    },
    "0xf709-0x20000" : {
      "Action" : 10,
      "Text" : "[17;2~"
    },
    "0xf70c-0x20000" : {
      "Action" : 10,
      "Text" : "[20;2~"
    },
    "0xf729-0x20000" : {
      "Action" : 10,
      "Text" : "[1;2H"
    },
    "0xf72b-0x40000" : {
      "Action" : 10,
      "Text" : "[1;5F"
    },
    "0xf705-0x20000" : {
      "Action" : 10,
      "Text" : "[1;2Q"
    },
    "0xf703-0x260000" : {
      "Action" : 10,
      "Text" : "[1;6C"
    },
    "0xf700-0x220000" : {
      "Action" : 10,
      "Text" : "[1;2A"
    },
    "0xf701-0x280000" : {
      "Action" : 11,
      "Text" : "0x1b 0x1b 0x5b 0x42"
    },
    "0x38-0x40000" : {
      "Action" : 11,
      "Text" : "0x7f"
    },
    "0x33-0x40000" : {
      "Action" : 11,
      "Text" : "0x1b"
    },
    "0xf703-0x220000" : {
      "Action" : 10,
      "Text" : "[1;2C"
    },
    "0xf701-0x240000" : {
      "Action" : 10,
      "Text" : "[1;5B"
    },
    "0xf70d-0x20000" : {
      "Action" : 10,
      "Text" : "[21;2~"
    },
    "0xf702-0x260000" : {
      "Action" : 10,
      "Text" : "[1;6D"
    },
    "0xf729-0x40000" : {
      "Action" : 10,
      "Text" : "[1;5H"
    },
    "0xf706-0x20000" : {
      "Action" : 10,
      "Text" : "[1;2R"
    },
    "0x34-0x40000" : {
      "Action" : 11,
      "Text" : "0x1c"
    },
    "0xf700-0x280000" : {
      "Action" : 11,
      "Text" : "0x1b 0x1b 0x5b 0x41"
    },
    "0x2d-0x40000" : {
      "Action" : 11,
      "Text" : "0x1f"
    },
    "0xf70e-0x20000" : {
      "Action" : 10,
      "Text" : "[23;2~"
    },
    "0xf702-0x220000" : {
      "Action" : 10,
      "Text" : "[1;2D"
    },
    "0xf700-0x240000" : {
      "Action" : 10,
      "Text" : "[1;5A"
    },
    "0xf707-0x20000" : {
      "Action" : 10,
      "Text" : "[1;2S"
    },
    "0xf70a-0x20000" : {
      "Action" : 10,
      "Text" : "[18;2~"
    },
    "0x35-0x40000" : {
      "Action" : 11,
      "Text" : "0x1d"
    },
    "0xf70f-0x20000" : {
      "Action" : 10,
      "Text" : "[24;2~"
    },
    "0xf701-0x260000" : {
      "Action" : 10,
      "Text" : "[1;6B"
    },
    "0xf72b-0x20000" : {
      "Action" : 10,
      "Text" : "[1;2F"
    },
    "0x36-0x40000" : {
      "Action" : 11,
      "Text" : "0x1e"
    },
    "0xf708-0x20000" : {
      "Action" : 10,
      "Text" : "[15;2~"
    },
    "0xf701-0x220000" : {
      "Action" : 10,
      "Text" : "[1;2B"
    },
    "0xf70b-0x20000" : {
      "Action" : 10,
      "Text" : "[19;2~"
    },
    "0xf704-0x20000" : {
      "Action" : 10,
      "Text" : "[1;2P"
    }
  },
  "Log Directory" : "",
  "Use Canonical Parser" : false,
  "Ansi 14 Color" : {
    "Green Component" : 1,
    "Red Component" : 0.3333333432674408,
    "Blue Component" : 1
  },
  "Ansi 2 Color" : {
    "Green Component" : 0.73333334922790527,
    "Red Component" : 0,
    "Blue Component" : 0
  },
  "Background Image Is Tiled" : false,
  "Send Code When Idle" : false,
  "ASCII Anti Aliased" : true,
  "Tags" : [

  ],
  "Ansi 9 Color" : {
    "Green Component" : 0.3333333432674408,
    "Red Component" : 1,
    "Blue Component" : 0.3333333432674408
  },
  "Use Bold Font" : true,
  "Silence Bell" : false,
  "Ansi 12 Color" : {
    "Green Component" : 0.3333333432674408,
    "Red Component" : 0.3333333432674408,
    "Blue Component" : 1
  },
  "Window Type" : 1,
  "Allow Title Reporting" : false,
  "Use Bright Bold" : true,
  "Cursor Text Color" : {
    "Green Component" : 1,
    "Red Component" : 1,
    "Blue Component" : 1
  },
  "Default Bookmark" : "No",
  "Cursor Color" : {
    "Green Component" : 0.73333334922790527,
    "Red Component" : 0.73333334922790527,
    "Blue Component" : 0.73333334922790527
  },
  "Disable Smcup Rmcup" : false,
  "Name" : "aapit-dark",
  "Blinking Cursor" : true,
  "Guid" : "6EC6E12D-5071-4CE7-B03C-C5E4F3B1D0B2",
  "Ansi 1 Color" : {
    "Green Component" : 0,
    "Red Component" : 0.73333334922790527,
    "Blue Component" : 0
  },
  "Idle Code" : 0,
  "Ansi 10 Color" : {
    "Green Component" : 1,
    "Red Component" : 0.3333333432674408,
    "Blue Component" : 0.3333333432674408
  },
  "Ansi 8 Color" : {
    "Green Component" : 0.3333333432674408,
    "Red Component" : 0.3333333432674408,
    "Blue Component" : 0.3333333432674408
  },
  "Badge Color" : {
    "Red Component" : 1,
    "Color Space" : "sRGB",
    "Blue Component" : 0,
    "Alpha Component" : 0.5,
    "Green Component" : 0.1491314172744751
  },
  "Automatically Log" : false,
  "Smart Cursor Color" : true,
  "Semantic History" : {
    "text" : "",
    "action" : "best editor",
    "editor" : "com.sublimetext.3"
  },
  "Ambiguous Double Width" : false,
  "Blur Radius" : 2,
  "Ansi 0 Color" : {
    "Green Component" : 0,
    "Red Component" : 0,
    "Blue Component" : 0
  },
  "Cursor Type" : 2,
  "Blur" : false,
  "Normal Font" : "Monaco 15",
  "Vertical Spacing" : 1,
  "Disable Printing" : false,
  "Ansi 7 Color" : {
    "Green Component" : 0.73333334922790527,
    "Red Component" : 0.73333334922790527,
    "Blue Component" : 0.73333334922790527
  },
  "Command" : "",
  "Terminal Type" : "xterm",
  "Horizontal Spacing" : 1,
  "Option Key Sends" : 0,
  "Blink Allowed" : false,
  "Minimum Contrast" : 0,
  "Ansi 15 Color" : {
    "Green Component" : 1,
    "Red Component" : 1,
    "Blue Component" : 1
  },
  "Ansi 6 Color" : {
    "Green Component" : 0.73333334922790527,
    "Red Component" : 0,
    "Blue Component" : 0.73333334922790527
  },
  "Transparency" : 0,
  "Initial Text" : "",
  "Background Color" : {
    "Green Component" : 0,
    "Red Component" : 0,
    "Blue Component" : 0
  },
  "Screen" : -1,
  "Non Ascii Font" : "Monaco 15",
  "Ansi 13 Color" : {
    "Green Component" : 0.3333333432674408,
    "Red Component" : 1,
    "Blue Component" : 1
  },
  "Columns" : 80,
  "Visual Bell" : true,
  "Custom Directory" : "Recycle",
  "Ansi 5 Color" : {
    "Green Component" : 0,
    "Red Component" : 0.73333334922790527,
    "Blue Component" : 0.73333334922790527
  },
  "Set Local Environment Vars" : true
},
{
  "Working Directory" : "\/Users\/david",
  "Prompt Before Closing 2" : 0,
  "Selected Text Color" : {
    "Green Component" : 0.73772752285003662,
    "Blue Component" : 0.72799122333526611,
    "Red Component" : 0.72378784418106079
  },
  "Rows" : 25,
  "Ansi 11 Color" : {
    "Green Component" : 0.44065150618553162,
    "Blue Component" : 0.20107564330101013,
    "Red Component" : 0.76750457286834717
  },
  "Use Italic Font" : false,
  "Foreground Color" : {
    "Green Component" : 0.73772752285003662,
    "Blue Component" : 0.72799122333526611,
    "Red Component" : 0.72378784418106079
  },
  "Right Option Key Sends" : 0,
  "Character Encoding" : 4,
  "Selection Color" : {
    "Green Component" : 0.17529888451099396,
    "Blue Component" : 0.19518557190895081,
    "Red Component" : 0.16332042217254639
  },
  "Triggers" : [

  ],
  "Blend" : 0.094888070913461547,
  "Mouse Reporting" : true,
  "Ansi 4 Color" : {
    "Green Component" : 0.46348986029624939,
    "Blue Component" : 0.63280379772186279,
    "Red Component" : 0.3079511821269989
  },
  "Non-ASCII Anti Aliased" : true,
  "Sync Title" : false,
  "Disable Window Resizing" : true,
  "Close Sessions On End" : true,
  "Jobs to Ignore" : [
    "rlogin",
    "ssh",
    "slogin",
    "telnet"
  ],
  "Scrollback With Status Bar" : false,
  "Scrollback Lines" : 5000,
  "Scrollback in Alternate Screen" : true,
  "Hide After Opening" : false,
  "Flashing Bell" : false,
  "Cursor Guide Color" : {
    "Red Component" : 0.70213186740875244,
    "Color Space" : "sRGB",
    "Blue Component" : 1,
    "Alpha Component" : 0.25,
    "Green Component" : 0.9268307089805603
  },
  "BM Growl" : true,
  "Ansi 3 Color" : {
    "Green Component" : 0.65007597208023071,
    "Blue Component" : 0.2083030492067337,
    "Red Component" : 0.77161651849746704
  },
  "Link Color" : {
    "Red Component" : 0,
    "Color Space" : "sRGB",
    "Blue Component" : 0.73423302173614502,
    "Alpha Component" : 1,
    "Green Component" : 0.35916060209274292
  },
  "Shortcut" : "",
  "Background Image Location" : "\/Users\/david\/Pictures\/wallpapers\/martijn-kort-203179155-dark.jpg",
  "Bold Color" : {
    "Green Component" : 1,
    "Blue Component" : 0.69725716114044189,
    "Red Component" : 0.99575066566467285
  },
  "Unlimited Scrollback" : false,
  "Custom Command" : "No",
  "Smart Selection Rules" : [
    {
      "notes" : "Word bounded by whitespace",
      "regex" : "\\S+",
      "precision" : "low"
    },
    {
      "notes" : "C++ namespace::identifier",
      "regex" : "([a-zA-Z0-9_]+::)+[a-zA-Z0-9_]+",
      "precision" : "normal"
    },
    {
      "notes" : "Paths",
      "regex" : "\\~?\/?([[:letter:][:number:]._-]+\/+)+[[:letter:][:number:]._-]+\/?",
      "precision" : "normal"
    },
    {
      "notes" : "Quoted string",
      "regex" : "@?\"(?:[^\"\\\\]|\\\\.)*\"",
      "precision" : "normal"
    },
    {
      "notes" : "Java\/Python include paths",
      "regex" : "([[:letter:][:number:]._]+\\.)+[[:letter:][:number:]._]+",
      "precision" : "normal"
    },
    {
      "notes" : "mailto URL",
      "regex" : "\\bmailto:([a-z0-9A-Z_]+@)?([a-zA-Z0-9\\-]+\\.)*[a-zA-Z0-9\\-]+\\b",
      "precision" : "normal"
    },
    {
      "notes" : "Obj-C selector",
      "regex" : "@selector\\([^)]+\\)",
      "precision" : "high"
    },
    {
      "notes" : "email address",
      "regex" : "\\b[A-Za-z0-9._%+-]+@[A-Za-z0-9.-]+\\.[A-Za-z]{2,4}\\b",
      "precision" : "high"
    },
    {
      "notes" : "HTTP URL",
      "regex" : "https?:\/\/([a-z0-9A-Z]+(:[a-zA-Z0-9]+)?@)?[a-z0-9A-Z]+(\\.[a-z0-9A-Z]+)*((:[0-9]+)?)(\/[a-zA-Z0-9;\/\\.\\-_+%~?&@=#\\(\\)]*)?",
      "precision" : "very_high"
    },
    {
      "notes" : "SSH URL",
      "regex" : "\\bssh:([a-z0-9A-Z_]+@)?([a-zA-Z0-9\\-]+\\.)*[a-zA-Z0-9\\-]+\\b",
      "precision" : "very_high"
    },
    {
      "notes" : "Telnet URL",
      "regex" : "\\btelnet:([a-z0-9A-Z_]+@)?([a-zA-Z0-9\\-]+\\.)*[a-zA-Z0-9\\-]+\\b",
      "precision" : "very_high"
    }
  ],
  "Keyboard Map" : {
    "0xf704-0x20000" : {
      "Action" : 10,
      "Text" : "[1;2P"
    },
    "0xf700-0x260000" : {
      "Action" : 10,
      "Text" : "[1;6A"
    },
    "0x37-0x40000" : {
      "Action" : 11,
      "Text" : "0x1f"
    },
    "0x32-0x40000" : {
      "Action" : 11,
      "Text" : "0x00"
    },
    "0xf709-0x20000" : {
      "Action" : 10,
      "Text" : "[17;2~"
    },
    "0xf70c-0x20000" : {
      "Action" : 10,
      "Text" : "[20;2~"
    },
    "0xf729-0x20000" : {
      "Action" : 10,
      "Text" : "[1;2H"
    },
    "0xf72b-0x40000" : {
      "Action" : 10,
      "Text" : "[1;5F"
    },
    "0xf705-0x20000" : {
      "Action" : 10,
      "Text" : "[1;2Q"
    },
    "0xf703-0x260000" : {
      "Action" : 10,
      "Text" : "[1;6C"
    },
    "0xf700-0x220000" : {
      "Action" : 10,
      "Text" : "[1;2A"
    },
    "0xf701-0x280000" : {
      "Action" : 11,
      "Text" : "0x1b 0x1b 0x5b 0x42"
    },
    "0x38-0x40000" : {
      "Action" : 11,
      "Text" : "0x7f"
    },
    "0x33-0x40000" : {
      "Action" : 11,
      "Text" : "0x1b"
    },
    "0xf703-0x220000" : {
      "Action" : 10,
      "Text" : "[1;2C"
    },
    "0xf701-0x240000" : {
      "Action" : 10,
      "Text" : "[1;5B"
    },
    "0xf70d-0x20000" : {
      "Action" : 10,
      "Text" : "[21;2~"
    },
    "0xf702-0x260000" : {
      "Action" : 10,
      "Text" : "[1;6D"
    },
    "0xf729-0x40000" : {
      "Action" : 10,
      "Text" : "[1;5H"
    },
    "0xf706-0x20000" : {
      "Action" : 10,
      "Text" : "[1;2R"
    },
    "0x34-0x40000" : {
      "Action" : 11,
      "Text" : "0x1c"
    },
    "0xf700-0x280000" : {
      "Action" : 11,
      "Text" : "0x1b 0x1b 0x5b 0x41"
    },
    "0x2d-0x40000" : {
      "Action" : 11,
      "Text" : "0x1f"
    },
    "0xf70e-0x20000" : {
      "Action" : 10,
      "Text" : "[23;2~"
    },
    "0xf702-0x220000" : {
      "Action" : 10,
      "Text" : "[1;2D"
    },
    "0xf700-0x240000" : {
      "Action" : 10,
      "Text" : "[1;5A"
    },
    "0xf707-0x20000" : {
      "Action" : 10,
      "Text" : "[1;2S"
    },
    "0xf70a-0x20000" : {
      "Action" : 10,
      "Text" : "[18;2~"
    },
    "0x35-0x40000" : {
      "Action" : 11,
      "Text" : "0x1d"
    },
    "0xf70f-0x20000" : {
      "Action" : 10,
      "Text" : "[24;2~"
    },
    "0xf701-0x260000" : {
      "Action" : 10,
      "Text" : "[1;6B"
    },
    "0xf72b-0x20000" : {
      "Action" : 10,
      "Text" : "[1;2F"
    },
    "0x36-0x40000" : {
      "Action" : 11,
      "Text" : "0x1e"
    },
    "0xf708-0x20000" : {
      "Action" : 10,
      "Text" : "[15;2~"
    },
    "0xf701-0x220000" : {
      "Action" : 10,
      "Text" : "[1;2B"
    },
    "0xf70b-0x20000" : {
      "Action" : 10,
      "Text" : "[19;2~"
    }
  },
  "Log Directory" : "",
  "Use Canonical Parser" : false,
  "Ansi 14 Color" : {
    "Green Component" : 0.43889713287353516,
    "Blue Component" : 0.42635926604270935,
    "Red Component" : 0.1796993762254715
  },
  "Ansi 2 Color" : {
    "Green Component" : 0.60448122024536133,
    "Blue Component" : 0.23052853345870972,
    "Red Component" : 0.52787607908248901
  },
  "Background Image Is Tiled" : false,
  "Send Code When Idle" : false,
  "ASCII Anti Aliased" : true,
  "Tags" : [

  ],
  "Ansi 9 Color" : {
    "Green Component" : 0,
    "Blue Component" : 0.11970168352127075,
    "Red Component" : 0.98592376708984375
  },
  "Use Bold Font" : true,
  "Silence Bell" : false,
  "Ansi 12 Color" : {
    "Green Component" : 0.42590731382369995,
    "Blue Component" : 0.89109110832214355,
    "Red Component" : 0.093434453010559082
  },
  "Window Type" : 1,
  "Allow Title Reporting" : false,
  "Use Bright Bold" : true,
  "Has Hotkey" : false,
  "Cursor Text Color" : {
    "Green Component" : 0.089508526027202606,
    "Blue Component" : 0.089510045945644379,
    "Red Component" : 0.089511208236217499
  },
  "Default Bookmark" : "No",
  "Cursor Color" : {
    "Green Component" : 0.24263888597488403,
    "Blue Component" : 0.098565541207790375,
    "Red Component" : 0.9727436900138855
  },
  "Disable Smcup Rmcup" : false,
  "Name" : "aapit-darkish",
  "Blinking Cursor" : true,
  "Guid" : "3816D330-BCE5-4A4D-A0C8-85392522B896",
  "Ansi 1 Color" : {
    "Green Component" : 0.24612078070640564,
    "Blue Component" : 0.28296563029289246,
    "Red Component" : 0.74655872583389282
  },
  "Ansi 8 Color" : {
    "Green Component" : 0.53847712278366089,
    "Blue Component" : 0.52966117858886719,
    "Red Component" : 0.53400516510009766
  },
  "Ansi 10 Color" : {
    "Green Component" : 0.44594758749008179,
    "Blue Component" : 0.18262514472007751,
    "Red Component" : 0.058273889124393463
  },
  "Idle Code" : 0,
  "Badge Color" : {
    "Red Component" : 1,
    "Color Space" : "sRGB",
    "Blue Component" : 0,
    "Alpha Component" : 0.5,
    "Green Component" : 0.1491314172744751
  },
  "Automatically Log" : false,
  "Smart Cursor Color" : true,
  "Semantic History" : {
    "text" : "",
    "action" : "best editor",
    "editor" : "com.sublimetext.3"
  },
  "Ambiguous Double Width" : false,
  "Blur Radius" : 11.36408034581218,
  "Ansi 0 Color" : {
    "Green Component" : 0.23855249583721161,
    "Blue Component" : 0.26370203495025635,
    "Red Component" : 0.22909823060035706
  },
  "Cursor Type" : 2,
  "Blur" : true,
  "Normal Font" : "Monaco 15",
  "Vertical Spacing" : 1,
  "Disable Printing" : false,
  "Ansi 7 Color" : {
    "Green Component" : 0.73772752285003662,
    "Blue Component" : 0.72799122333526611,
    "Red Component" : 0.72378784418106079
  },
  "Command" : "",
  "Terminal Type" : "xterm",
  "Horizontal Spacing" : 1,
  "Option Key Sends" : 0,
  "Only The Default BG Color Uses Transparency" : true,
  "Blink Allowed" : false,
  "Minimum Contrast" : 0,
  "Ansi 15 Color" : {
    "Green Component" : 1,
    "Blue Component" : 0.72441869974136353,
    "Red Component" : 0.99088609218597412
  },
  "Open Toolbelt" : false,
  "Ansi 6 Color" : {
    "Green Component" : 0.56019961833953857,
    "Blue Component" : 0.64178985357284546,
    "Red Component" : 0.34018850326538086
  },
  "Transparency" : 0,
  "Initial Text" : "",
  "Background Color" : {
    "Green Component" : 0.12050691246986389,
    "Blue Component" : 0.12050896137952805,
    "Red Component" : 0.1205105185508728
  },
  "Screen" : -1,
  "Bound Hosts" : [

  ],
  "Non Ascii Font" : "Monaco 15",
  "Ansi 13 Color" : {
    "Green Component" : 0,
    "Blue Component" : 0.40404337644577026,
    "Red Component" : 0.98593467473983765
  },
  "Columns" : 80,
  "Visual Bell" : true,
  "Custom Directory" : "Recycle",
  "Ansi 5 Color" : {
    "Green Component" : 0.36032408475875854,
    "Blue Component" : 0.5548633337020874,
    "Red Component" : 0.5216478705406189
  },
  "Set Local Environment Vars" : true
},
{
  "Working Directory" : "\/Users\/david",
  "Prompt Before Closing 2" : 0,
  "Selected Text Color" : {
    "Red Component" : 0.34509803921568627,
    "Color Space" : "sRGB",
    "Blue Component" : 0.45882352941176469,
    "Green Component" : 0.43137254901960786
  },
  "Rows" : 25,
  "Ansi 11 Color" : {
    "Red Component" : 0.396078431372549,
    "Color Space" : "sRGB",
    "Blue Component" : 0.51372549019607838,
    "Green Component" : 0.4823529411764706
  },
  "Use Italic Font" : false,
  "Foreground Color" : {
    "Red Component" : 0.396078431372549,
    "Color Space" : "sRGB",
    "Blue Component" : 0.51372549019607838,
    "Green Component" : 0.4823529411764706
  },
  "Right Option Key Sends" : 0,
  "Character Encoding" : 4,
  "Selection Color" : {
    "Red Component" : 0.93333333333333335,
    "Color Space" : "sRGB",
    "Blue Component" : 0.83529411764705885,
    "Green Component" : 0.90980392156862744
  },
  "Triggers" : [

  ],
  "Blend" : 0.30000001192092896,
  "Mouse Reporting" : true,
  "Ansi 4 Color" : {
    "Red Component" : 0.14901960784313725,
    "Color Space" : "sRGB",
    "Blue Component" : 0.82352941176470584,
    "Green Component" : 0.54509803921568623
  },
  "Non-ASCII Anti Aliased" : true,
  "Sync Title" : false,
  "Disable Window Resizing" : true,
  "Close Sessions On End" : true,
  "Jobs to Ignore" : [
    "rlogin",
    "ssh",
    "slogin",
    "telnet"
  ],
  "Scrollback With Status Bar" : false,
  "Scrollback Lines" : 5000,
  "Scrollback in Alternate Screen" : true,
  "Hide After Opening" : false,
  "Flashing Bell" : false,
  "Cursor Guide Color" : {
    "Red Component" : 0.70213186740875244,
    "Color Space" : "sRGB",
    "Blue Component" : 1,
    "Alpha Component" : 0.25,
    "Green Component" : 0.9268307089805603
  },
  "BM Growl" : true,
  "Ansi 3 Color" : {
    "Red Component" : 0.70980392156862748,
    "Color Space" : "sRGB",
    "Blue Component" : 0,
    "Green Component" : 0.53725490196078429
  },
  "Link Color" : {
    "Red Component" : 0,
    "Color Space" : "sRGB",
    "Blue Component" : 0.73423302173614502,
    "Alpha Component" : 1,
    "Green Component" : 0.35916060209274292
  },
  "Shortcut" : "",
  "Background Image Location" : "",
  "Bold Color" : {
    "Red Component" : 0.34509803921568627,
    "Color Space" : "sRGB",
    "Blue Component" : 0.45882352941176469,
    "Green Component" : 0.43137254901960786
  },
  "Unlimited Scrollback" : false,
  "Custom Command" : "No",
  "Smart Selection Rules" : [
    {
      "notes" : "Word bounded by whitespace",
      "regex" : "\\S+",
      "precision" : "low"
    },
    {
      "notes" : "C++ namespace::identifier",
      "regex" : "([a-zA-Z0-9_]+::)+[a-zA-Z0-9_]+",
      "precision" : "normal"
    },
    {
      "notes" : "Paths",
      "regex" : "\\~?\/?([[:letter:][:number:]._-]+\/+)+[[:letter:][:number:]._-]+\/?",
      "precision" : "normal"
    },
    {
      "notes" : "Quoted string",
      "regex" : "@?\"(?:[^\"\\\\]|\\\\.)*\"",
      "precision" : "normal"
    },
    {
      "notes" : "Java\/Python include paths",
      "regex" : "([[:letter:][:number:]._]+\\.)+[[:letter:][:number:]._]+",
      "precision" : "normal"
    },
    {
      "notes" : "mailto URL",
      "regex" : "\\bmailto:([a-z0-9A-Z_]+@)?([a-zA-Z0-9\\-]+\\.)*[a-zA-Z0-9\\-]+\\b",
      "precision" : "normal"
    },
    {
      "notes" : "Obj-C selector",
      "regex" : "@selector\\([^)]+\\)",
      "precision" : "high"
    },
    {
      "notes" : "email address",
      "regex" : "\\b[A-Za-z0-9._%+-]+@[A-Za-z0-9.-]+\\.[A-Za-z]{2,4}\\b",
      "precision" : "high"
    },
    {
      "notes" : "HTTP URL",
      "regex" : "https?:\/\/([a-z0-9A-Z]+(:[a-zA-Z0-9]+)?@)?[a-z0-9A-Z]+(\\.[a-z0-9A-Z]+)*((:[0-9]+)?)(\/[a-zA-Z0-9;\/\\.\\-_+%~?&@=#\\(\\)]*)?",
      "precision" : "very_high"
    },
    {
      "notes" : "SSH URL",
      "regex" : "\\bssh:([a-z0-9A-Z_]+@)?([a-zA-Z0-9\\-]+\\.)*[a-zA-Z0-9\\-]+\\b",
      "precision" : "very_high"
    },
    {
      "notes" : "Telnet URL",
      "regex" : "\\btelnet:([a-z0-9A-Z_]+@)?([a-zA-Z0-9\\-]+\\.)*[a-zA-Z0-9\\-]+\\b",
      "precision" : "very_high"
    }
  ],
  "Keyboard Map" : {
    "0xf700-0x260000" : {
      "Action" : 10,
      "Text" : "[1;6A"
    },
    "0x37-0x40000" : {
      "Action" : 11,
      "Text" : "0x1f"
    },
    "0x32-0x40000" : {
      "Action" : 11,
      "Text" : "0x00"
    },
    "0xf709-0x20000" : {
      "Action" : 10,
      "Text" : "[17;2~"
    },
    "0xf70c-0x20000" : {
      "Action" : 10,
      "Text" : "[20;2~"
    },
    "0xf729-0x20000" : {
      "Action" : 10,
      "Text" : "[1;2H"
    },
    "0xf72b-0x40000" : {
      "Action" : 10,
      "Text" : "[1;5F"
    },
    "0xf705-0x20000" : {
      "Action" : 10,
      "Text" : "[1;2Q"
    },
    "0xf703-0x260000" : {
      "Action" : 10,
      "Text" : "[1;6C"
    },
    "0xf700-0x220000" : {
      "Action" : 10,
      "Text" : "[1;2A"
    },
    "0xf701-0x280000" : {
      "Action" : 11,
      "Text" : "0x1b 0x1b 0x5b 0x42"
    },
    "0x38-0x40000" : {
      "Action" : 11,
      "Text" : "0x7f"
    },
    "0x33-0x40000" : {
      "Action" : 11,
      "Text" : "0x1b"
    },
    "0xf703-0x220000" : {
      "Action" : 10,
      "Text" : "[1;2C"
    },
    "0xf701-0x240000" : {
      "Action" : 10,
      "Text" : "[1;5B"
    },
    "0xf70d-0x20000" : {
      "Action" : 10,
      "Text" : "[21;2~"
    },
    "0xf702-0x260000" : {
      "Action" : 10,
      "Text" : "[1;6D"
    },
    "0xf729-0x40000" : {
      "Action" : 10,
      "Text" : "[1;5H"
    },
    "0xf706-0x20000" : {
      "Action" : 10,
      "Text" : "[1;2R"
    },
    "0x34-0x40000" : {
      "Action" : 11,
      "Text" : "0x1c"
    },
    "0xf700-0x280000" : {
      "Action" : 11,
      "Text" : "0x1b 0x1b 0x5b 0x41"
    },
    "0x2d-0x40000" : {
      "Action" : 11,
      "Text" : "0x1f"
    },
    "0xf70e-0x20000" : {
      "Action" : 10,
      "Text" : "[23;2~"
    },
    "0xf702-0x220000" : {
      "Action" : 10,
      "Text" : "[1;2D"
    },
    "0xf700-0x240000" : {
      "Action" : 10,
      "Text" : "[1;5A"
    },
    "0xf707-0x20000" : {
      "Action" : 10,
      "Text" : "[1;2S"
    },
    "0xf70a-0x20000" : {
      "Action" : 10,
      "Text" : "[18;2~"
    },
    "0x35-0x40000" : {
      "Action" : 11,
      "Text" : "0x1d"
    },
    "0xf70f-0x20000" : {
      "Action" : 10,
      "Text" : "[24;2~"
    },
    "0xf701-0x260000" : {
      "Action" : 10,
      "Text" : "[1;6B"
    },
    "0xf72b-0x20000" : {
      "Action" : 10,
      "Text" : "[1;2F"
    },
    "0x36-0x40000" : {
      "Action" : 11,
      "Text" : "0x1e"
    },
    "0xf708-0x20000" : {
      "Action" : 10,
      "Text" : "[15;2~"
    },
    "0xf701-0x220000" : {
      "Action" : 10,
      "Text" : "[1;2B"
    },
    "0xf70b-0x20000" : {
      "Action" : 10,
      "Text" : "[19;2~"
    },
    "0xf704-0x20000" : {
      "Action" : 10,
      "Text" : "[1;2P"
    }
  },
  "Log Directory" : "",
  "Use Canonical Parser" : false,
  "Ansi 14 Color" : {
    "Red Component" : 0.57647058823529407,
    "Color Space" : "sRGB",
    "Blue Component" : 0.63137254901960782,
    "Green Component" : 0.63137254901960782
  },
  "Ansi 2 Color" : {
    "Red Component" : 0.52156862745098043,
    "Color Space" : "sRGB",
    "Blue Component" : 0,
    "Green Component" : 0.59999999999999998
  },
  "Background Image Is Tiled" : false,
  "Send Code When Idle" : false,
  "ASCII Anti Aliased" : true,
  "Tags" : [

  ],
  "Ansi 9 Color" : {
    "Red Component" : 0.79607843137254897,
    "Color Space" : "sRGB",
    "Blue Component" : 0.086274509803921567,
    "Green Component" : 0.29411764705882354
  },
  "Use Bold Font" : true,
  "Silence Bell" : false,
  "Ansi 12 Color" : {
    "Red Component" : 0.51372549019607838,
    "Color Space" : "sRGB",
    "Blue Component" : 0.58823529411764708,
    "Green Component" : 0.58039215686274515
  },
  "Window Type" : 1,
  "Allow Title Reporting" : false,
  "Use Bright Bold" : true,
  "Cursor Text Color" : {
    "Red Component" : 0.93333333333333335,
    "Color Space" : "sRGB",
    "Blue Component" : 0.83529411764705885,
    "Green Component" : 0.90980392156862744
  },
  "Default Bookmark" : "No",
  "Cursor Color" : {
    "Red Component" : 0.396078431372549,
    "Color Space" : "sRGB",
    "Blue Component" : 0.51372549019607838,
    "Green Component" : 0.4823529411764706
  },
  "Disable Smcup Rmcup" : false,
  "Name" : "aapit-light",
  "Blinking Cursor" : true,
  "Guid" : "180167C7-4D8C-4582-92DB-A7ABEB72DFB2",
  "Ansi 1 Color" : {
    "Red Component" : 0.86274509803921573,
    "Color Space" : "sRGB",
    "Blue Component" : 0.18431372549019609,
    "Green Component" : 0.19607843137254902
  },
  "Idle Code" : 0,
  "Ansi 10 Color" : {
    "Red Component" : 0.34509803921568627,
    "Color Space" : "sRGB",
    "Blue Component" : 0.45882352941176469,
    "Green Component" : 0.43137254901960786
  },
  "Ansi 8 Color" : {
    "Red Component" : 0,
    "Color Space" : "sRGB",
    "Blue Component" : 0.21176470588235294,
    "Green Component" : 0.16862745098039217
  },
  "Badge Color" : {
    "Red Component" : 1,
    "Color Space" : "sRGB",
    "Blue Component" : 0,
    "Alpha Component" : 0.5,
    "Green Component" : 0.1491314172744751
  },
  "Automatically Log" : false,
  "Smart Cursor Color" : true,
  "Semantic History" : {
    "text" : "",
    "action" : "best editor",
    "editor" : "com.sublimetext.3"
  },
  "Ambiguous Double Width" : false,
  "Blur Radius" : 2,
  "Ansi 0 Color" : {
    "Red Component" : 0.027450980392156862,
    "Color Space" : "sRGB",
    "Blue Component" : 0.25882352941176473,
    "Green Component" : 0.21176470588235294
  },
  "Cursor Type" : 2,
  "Blur" : false,
  "Normal Font" : "Monaco 15",
  "Vertical Spacing" : 1,
  "Disable Printing" : false,
  "Ansi 7 Color" : {
    "Red Component" : 0.93333333333333335,
    "Color Space" : "sRGB",
    "Blue Component" : 0.83529411764705885,
    "Green Component" : 0.90980392156862744
  },
  "Command" : "",
  "Terminal Type" : "xterm",
  "Horizontal Spacing" : 1,
  "Option Key Sends" : 0,
  "Blink Allowed" : false,
  "Minimum Contrast" : 0,
  "Ansi 15 Color" : {
    "Red Component" : 0.99215686274509807,
    "Color Space" : "sRGB",
    "Blue Component" : 0.8901960784313725,
    "Green Component" : 0.96470588235294119
  },
  "Ansi 6 Color" : {
    "Red Component" : 0.16470588235294117,
    "Color Space" : "sRGB",
    "Blue Component" : 0.59607843137254901,
    "Green Component" : 0.63137254901960782
  },
  "Transparency" : 0,
  "Initial Text" : "",
  "Background Color" : {
    "Red Component" : 0.99215686274509807,
    "Color Space" : "sRGB",
    "Blue Component" : 0.8901960784313725,
    "Green Component" : 0.96470588235294119
  },
  "Screen" : -1,
  "Non Ascii Font" : "Monaco 15",
  "Ansi 13 Color" : {
    "Red Component" : 0.42352941176470588,
    "Color Space" : "sRGB",
    "Blue Component" : 0.7686274509803922,
    "Green Component" : 0.44313725490196076
  },
  "Columns" : 80,
  "Visual Bell" : true,
  "Custom Directory" : "Recycle",
  "Ansi 5 Color" : {
    "Red Component" : 0.82745098039215681,
    "Color Space" : "sRGB",
    "Blue Component" : 0.50980392156862742,
    "Green Component" : 0.21176470588235294
  },
  "Set Local Environment Vars" : true
}
]
}
